goto.py
goto_statement38-1.3.dist-info/LICENSE
goto_statement38-1.3.dist-info/METADATA
goto_statement38-1.3.dist-info/WHEEL
goto_statement38-1.3.dist-info/top_level.txt
goto_statement38-1.3.dist-info/RECORD
