Metadata-Version: 2.1
Name: goto-statement38
Version: 1.3
Summary: A function decorator that rewrites the bytecode, enabling goto in Python
Home-page: https://github.com/snoack/python-goto/
Author: allan-best
Author-email: qdzs0731@foxmail.com
License: UNKNOWN
Platform: UNKNOWN
Classifier: Development Status :: 5 - Production/Stable
Classifier: Intended Audience :: Developers
Classifier: License :: Public Domain
Classifier: Operating System :: OS Independent
Classifier: Programming Language :: Python :: 2
Classifier: Programming Language :: Python :: 3
Classifier: Topic :: Software Development :: Libraries :: Python Modules
